tests/__init__.py
tests/test_fairdata.py
tuttusa_datasets/__init__.py
tuttusa_datasets/cli.py
tuttusa_datasets/models.py
tuttusa_datasets/proxy_data.py
tuttusa_datasets/real_data.py
tuttusa_datasets/synthetic_data.py
tuttusa_datasets/tuttusa_datasets.py
tuttusa_datasets/utils.py
tuttusa_datasets/raw/__init__.py
tuttusa_datasets/raw/real/__init__.py
tuttusa_datasets-0.1.dist-info/AUTHORS.md
tuttusa_datasets-0.1.dist-info/LICENSE
tuttusa_datasets-0.1.dist-info/METADATA
tuttusa_datasets-0.1.dist-info/WHEEL
tuttusa_datasets-0.1.dist-info/top_level.txt
tuttusa_datasets-0.1.dist-info/RECORD
